stargen/__init__.py
stargen/__main__.py
stargen/stargen.py
stargen/modules/__init__.py
stargen/modules/abs_module.py
stargen/modules/combination.py
stargen/modules/crunch.py
stargen/modules/download.py
stargen/modules/keyword.py
stargen-0.8.6.dist-info/LICENSE
stargen-0.8.6.dist-info/METADATA
stargen-0.8.6.dist-info/WHEEL
stargen-0.8.6.dist-info/entry_points.txt
stargen-0.8.6.dist-info/top_level.txt
stargen-0.8.6.dist-info/RECORD
