Metadata-Version: 2.1
Name: stargen
Version: 0.8.6
Summary: Framework for wordlist generation, combination and expansion
Home-page: https://github.com/codeswhite/stargen
Author: Max G
Author-email: max3227@gmail.com
License: UNKNOWN
Platform: UNKNOWN
Classifier: Programming Language :: Python :: 3
Classifier: License :: OSI Approved :: MIT License
Classifier: Operating System :: OS Independent
Requires-Python: >=3.8
License-File: LICENSE
Requires-Dist: interutils
